{"stages":["Submission \u2192 decision","Decision \u2192 construction start","Construction \u2192 commissioning"],"buckets":[{"key":"SolarSmall","name":"Solar \u00b7 small (<10 MW)","total":11.6,"median":[1.9,7.1,2.6],"mean":[3.5,9.0,3.6],"n":[4286,792,775]},{"key":"SolarLarge","name":"Solar \u00b7 large (\u226510 MW)","total":17.4,"median":[5.5,8.2,3.7],"mean":[8.5,12.4,5.2],"n":[1232,292,234]},{"key":"Battery","name":"Battery","total":31.099999999999998,"median":[6.2,18.9,6.0],"mean":[9.2,20.3,8.9],"n":[1539,164,122]},{"key":"Bioenergy","name":"Bioenergy","total":38.4,"median":[4.8,19.5,14.1],"mean":[9.0,25.2,18.4],"n":[982,258,242]},{"key":"OnshoreSmall","name":"Onshore wind \u00b7 small (<10 MW)","total":42.0,"median":[11.4,23.1,7.5],"mean":[15.3,28.4,9.2],"n":[675,243,233]},{"key":"Hydro","name":"Hydro","total":43.099999999999994,"median":[6.9,18.5,17.7],"mean":[11.6,23.1,21.9],"n":[112,51,51]},{"key":"OnshoreLarge","name":"Onshore wind \u00b7 large (\u226510 MW)","total":65.8,"median":[24.8,27.3,13.7],"mean":[28.4,32.7,15.3],"n":[641,342,311]},{"key":"Offshore","name":"Offshore wind","total":71.8,"median":[18.9,35.5,17.4],"mean":[22.8,35.7,20.0],"n":[81,55,49]}],"bySize":{"Solar":[{"band":"<1 MW","median":[1.8,5.1,2.4],"mean":[2.5,7.3,3.3],"n":[2676,53,65]},{"band":"1\u20135 MW","median":[3.0,6.9,2.5],"mean":[4.8,8.5,3.8],"n":[876,300,292]},{"band":"5\u201310 MW","median":[3.9,7.5,2.8],"mean":[6.0,9.6,3.5],"n":[734,439,418]},{"band":"10\u201325 MW","median":[5.1,6.1,3.5],"mean":[8.0,8.8,4.2],"n":[436,186,170]},{"band":"25\u201350 MW","median":[10.3,15.3,5.8],"mean":[12.5,19.9,7.2],"n":[436,92,53]},{"band":"50\u2013100 MW","median":[12.8,8.2,17.0],"mean":[13.1,9.6,14.0],"n":[18,6,5]},{"band":"100+ MW","median":[17.5,26.1,27.0],"mean":[19.0,26.1,27.0],"n":[18,1,1]}],"OnshoreWind":[{"band":"<1 MW","median":[8.6,23.2,null],"mean":[11.2,23.2,null],"n":[137,2,0]},{"band":"1\u20135 MW","median":[11.2,21.3,6.0],"mean":[14.1,27.3,8.0],"n":[339,137,130]},{"band":"5\u201310 MW","median":[15.8,25.9,9.5],"mean":[20.2,29.9,10.8],"n":[199,104,103]},{"band":"10\u201325 MW","median":[21.8,26.0,11.4],"mean":[25.1,30.4,12.4],"n":[290,175,169]},{"band":"25\u201350 MW","median":[25.1,32.6,15.0],"mean":[30.1,35.4,16.8],"n":[185,98,87]},{"band":"50\u2013100 MW","median":[32.6,36.5,19.8],"mean":[36.7,38.3,20.9],"n":[99,48,38]},{"band":"100+ MW","median":[34.5,23.0,23.0],"mean":[36.3,27.3,23.3],"n":[39,21,17]}],"Battery":[{"band":"<1 MW","median":[2.1,37.1,1.0],"mean":[2.9,37.1,3.0],"n":[241,1,16]},{"band":"1\u20135 MW","median":[3.3,7.0,1.0],"mean":[7.2,13.3,2.3],"n":[54,7,13]},{"band":"5\u201310 MW","median":[4.9,14.9,5.5],"mean":[9.8,14.2,11.2],"n":[69,6,6]},{"band":"10\u201325 MW","median":[6.7,17.9,5.0],"mean":[11.1,19.8,7.6],"n":[160,30,27]},{"band":"25\u201350 MW","median":[6.7,23.4,12.8],"mean":[9.5,22.5,13.7],"n":[307,47,30]},{"band":"50\u2013100 MW","median":[8.8,16.4,12.0],"mean":[11.5,18.7,13.5],"n":[165,23,12]},{"band":"100+ MW","median":[9.2,17.8,25.4],"mean":[11.2,20.2,25.4],"n":[183,20,2]}]},"sizeTechNames":{"Solar":"Solar","OnshoreWind":"Onshore wind","Battery":"Battery"}}